AUTHORS.md
LICENSE
MANIFEST.in
README.md
pyproject.toml
setup.py
scipydepr/__init__.py
scipydepr.egg-info/PKG-INFO
scipydepr.egg-info/SOURCES.txt
scipydepr.egg-info/dependency_links.txt
scipydepr.egg-info/not-zip-safe
scipydepr.egg-info/top_level.txt
scipydepr/special/__init__.py
scipydepr/special/cython_special.c
scipydepr/special/cython_special.pyx
scipydepr/special/special.c
scipydepr/special/special.py
scipydepr/special/version.py