Metadata-Version: 2.1
Name: scipydepr
Version: 0.0.1
Summary: Deprecated functions from Scipy (scipy.special), for those of us who need them
Home-page: http://github.com/vhaasteren/scipydepr/
Author: Rutger van Haasteren
Author-email: Rutger van Haasteren <rutger@vhaasteren.com>
License: BSD 3-Clause License
Project-URL: Homepage, https://github.com/vhaasteren/scipydepr
Project-URL: Bug Tracker, https://github.com/vhaasteren/scipydepr/issues
Classifier: Programming Language :: Python :: 3
Classifier: License :: OSI Approved :: BSD License
Classifier: Operating System :: OS Independent
Requires-Python: >=3.7
License-File: LICENSE
License-File: AUTHORS.md
